{
  "sides": [
    {
      "code": "left",
      "uz": "Чапда",
      "ru": "Слева"
    },
    {
      "code": "right",
      "uz": "Ўнгда",
      "ru": "Справа"
    },
    {
      "code": "both",
      "uz": "Иккаласи",
      "ru": "С обеих сторон"
    }
  ],
  "degrees": [
    {
      "code": "none",
      "uz": "Йўқ",
      "ru": "Нет",
      "is_norm": true
    },
    {
      "code": "I",
      "uz": "И даража",
      "ru": "I ст."
    },
    {
      "code": "II",
      "uz": "ИИ даража",
      "ru": "II ст."
    },
    {
      "code": "III",
      "uz": "ИИИ даража",
      "ru": "III ст."
    }
  ],
  "methods": [
    {
      "code": "rhinoscopy",
      "icon": "👃",
      "name": {
        "uz": "РИНОСКОПИЯ",
        "ru": "РИНОСКОПИЯ"
      },
      "sections": [
        {
          "code": "external_nose",
          "name": {
            "uz": "Ташқи бурун",
            "ru": "Наружный нос"
          },
          "fields": [
            {
              "code": "state",
              "type": "radio",
              "options": [
                {
                  "code": "unchanged",
                  "uz": "Ўзгармаган",
                  "ru": "Не изменен",
                  "is_norm": true
                },
                {
                  "code": "deformed",
                  "uz": "Деформатсия",
                  "ru": "Деформация"
                }
              ]
            },
            {
              "code": "deformity_type",
              "type": "checkbox_multi",
              "visible_when": {
                "state": "deformed"
              },
              "options": [
                {
                  "code": "sunken",
                  "uz": "Чўкиш",
                  "ru": "Западение"
                },
                {
                  "code": "hump",
                  "uz": "Букрилик",
                  "ru": "Горбинка"
                },
                {
                  "code": "scoliosis",
                  "uz": "Сколиоз",
                  "ru": "Сколиоз"
                }
              ]
            },
            {
              "code": "side",
              "type": "side",
              "visible_when": {
                "state": "deformed"
              }
            },
            {
              "code": "part",
              "type": "radio",
              "visible_when": {
                "state": "deformed"
              },
              "options": [
                {
                  "code": "bone",
                  "uz": "Суяк қисми",
                  "ru": "Костная часть"
                },
                {
                  "code": "cartilage",
                  "uz": "Тоғай қисми",
                  "ru": "Хрящевая часть"
                }
              ]
            },
            {
              "code": "location",
              "type": "checkbox_multi",
              "visible_when": {
                "state": "deformed"
              },
              "options": [
                {
                  "code": "dorsum",
                  "uz": "Бурун орқаси",
                  "ru": "Спинка"
                },
                {
                  "code": "wings",
                  "uz": "Қанотлари",
                  "ru": "Крылья"
                },
                {
                  "code": "tip",
                  "uz": "Учи",
                  "ru": "Кончик"
                },
                {
                  "code": "nostrils",
                  "uz": "Бурун тешиклари",
                  "ru": "Ноздри"
                }
              ]
            }
          ]
        },
        {
          "code": "trigeminal",
          "name": {
            "uz": "Уч шохли нерв чиқиш нуқталари",
            "ru": "Точки выхода тройничного нерва"
          },
          "fields": [
            {
              "code": "state",
              "type": "radio",
              "options": [
                {
                  "code": "painless",
                  "uz": "Оғриқсиз",
                  "ru": "Безболезненны",
                  "is_norm": true
                },
                {
                  "code": "painful",
                  "uz": "Оғриқли",
                  "ru": "Болезненны"
                }
              ]
            },
            {
              "code": "side",
              "type": "side",
              "visible_when": {
                "state": "painful"
              }
            },
            {
              "code": "branch",
              "type": "checkbox_multi",
              "visible_when": {
                "state": "painful"
              },
              "options": [
                {
                  "code": "I",
                  "uz": "И шох",
                  "ru": "I ветвь"
                },
                {
                  "code": "II",
                  "uz": "ИИ шох",
                  "ru": "II ветвь"
                },
                {
                  "code": "III",
                  "uz": "ИИИ шох",
                  "ru": "III ветвь"
                }
              ]
            }
          ]
        },
        {
          "code": "breathing",
          "name": {
            "uz": "Бурун орқали нафас олиш",
            "ru": "Дыхание через нос"
          },
          "fields": [
            {
              "code": "state",
              "type": "radio",
              "options": [
                {
                  "code": "free",
                  "uz": "Еркин",
                  "ru": "Свободное",
                  "is_norm": true
                },
                {
                  "code": "difficult",
                  "uz": "Қийинлашган",
                  "ru": "Затруднено"
                },
                {
                  "code": "absent",
                  "uz": "Мавжуд емас",
                  "ru": "Отсутствует"
                }
              ]
            },
            {
              "code": "side",
              "type": "side",
              "visible_when": {
                "state": [
                  "difficult",
                  "absent"
                ]
              }
            }
          ]
        },
        {
          "code": "vestibule",
          "name": {
            "uz": "Бурун даҳлизи",
            "ru": "Преддверие"
          },
          "fields": [
            {
              "code": "state",
              "type": "radio",
              "options": [
                {
                  "code": "unchanged",
                  "uz": "Ўзгармаган",
                  "ru": "Не изменено",
                  "is_norm": true
                },
                {
                  "code": "narrowed",
                  "uz": "Торайган",
                  "ru": "Сужено"
                }
              ]
            },
            {
              "code": "side",
              "type": "side",
              "visible_when": {
                "state": "narrowed"
              }
            }
          ]
        },
        {
          "code": "olfaction",
          "name": {
            "uz": "Ҳид билиш",
            "ru": "Обоняние"
          },
          "fields": [
            {
              "code": "state",
              "type": "radio",
              "options": [
                {
                  "code": "preserved",
                  "uz": "Сақланган",
                  "ru": "Сохранено",
                  "is_norm": true
                },
                {
                  "code": "hyposmia",
                  "uz": "Гипосмия",
                  "ru": "Гипосмия"
                },
                {
                  "code": "anosmia",
                  "uz": "Аносмия",
                  "ru": "Аносмия"
                },
                {
                  "code": "hyperosmia",
                  "uz": "Гиперосмия",
                  "ru": "Гиперосмия"
                }
              ]
            },
            {
              "code": "side",
              "type": "side",
              "visible_when": {
                "state": [
                  "hyposmia",
                  "anosmia",
                  "hyperosmia"
                ]
              }
            }
          ]
        },
        {
          "code": "mucosa",
          "name": {
            "uz": "Шиллиқ қават",
            "ru": "Слизистая оболочка"
          },
          "fields": [
            {
              "code": "color",
              "type": "radio",
              "options": [
                {
                  "code": "pink",
                  "uz": "Пушти",
                  "ru": "Розовая",
                  "is_norm": true
                },
                {
                  "code": "pale_pink",
                  "uz": "Оқартирилган пушти",
                  "ru": "Бледно-розовая"
                },
                {
                  "code": "bluish",
                  "uz": "Кўкимтир",
                  "ru": "Синюшная"
                },
                {
                  "code": "hyperemic",
                  "uz": "Гиперемияланган",
                  "ru": "Гиперемирована"
                }
              ]
            },
            {
              "code": "moisture",
              "type": "radio",
              "options": [
                {
                  "code": "moist",
                  "uz": "Нам",
                  "ru": "Влажная",
                  "is_norm": true
                },
                {
                  "code": "dry",
                  "uz": "Қуруқ",
                  "ru": "Сухая"
                }
              ]
            },
            {
              "code": "condition",
              "type": "checkbox_multi",
              "options": [
                {
                  "code": "hypertrophied",
                  "uz": "Гипертрофияланган",
                  "ru": "Гипертрофирована"
                },
                {
                  "code": "ulcerated",
                  "uz": "Яраланган",
                  "ru": "Изъязвлена"
                }
              ]
            },
            {
              "code": "location",
              "type": "checkbox_multi",
              "options": [
                {
                  "code": "septum",
                  "uz": "Бурун тўсиғи соҳаси",
                  "ru": "Область перегородки носа"
                },
                {
                  "code": "turbinate_inferior",
                  "uz": "Пастки чиғаноқ",
                  "ru": "Нижняя носовая раковина"
                },
                {
                  "code": "turbinate_middle",
                  "uz": "Ўрта чиғаноқ",
                  "ru": "Средняя носовая раковина"
                },
                {
                  "code": "turbinate_superior",
                  "uz": "Юқори чиғаноқ",
                  "ru": "Верхняя носовая раковина"
                },
                {
                  "code": "meatus_inferior",
                  "uz": "Пастки бурун йўли",
                  "ru": "Нижний носовой ход"
                },
                {
                  "code": "meatus_middle",
                  "uz": "Ўрта бурун йўли",
                  "ru": "Средний носовой ход"
                },
                {
                  "code": "meatus_superior",
                  "uz": "Юқори бурун йўли",
                  "ru": "Верхний носовой ход"
                },
                {
                  "code": "end_anterior",
                  "uz": "Олдинги учи",
                  "ru": "Передний конец"
                },
                {
                  "code": "end_posterior",
                  "uz": "Орқа учи",
                  "ru": "Задний конец"
                }
              ]
            }
          ]
        },
        {
          "code": "septum",
          "name": {
            "uz": "Бурун тўсиғи",
            "ru": "Носовая перегородка"
          },
          "fields": [
            {
              "code": "state",
              "type": "radio",
              "options": [
                {
                  "code": "midline",
                  "uz": "Ўрта чизиқда",
                  "ru": "По средней линии",
                  "is_norm": true
                },
                {
                  "code": "curved",
                  "uz": "Қийшайган",
                  "ru": "Искривлена"
                }
              ]
            },
            {
              "code": "features",
              "type": "checkbox_multi",
              "visible_when": {
                "state": "curved"
              },
              "options": [
                {
                  "code": "bulge",
                  "uz": "Бўртма",
                  "ru": "Бугор"
                },
                {
                  "code": "ridge",
                  "uz": "Қирра",
                  "ru": "Гребень"
                },
                {
                  "code": "spike",
                  "uz": "Тиканча",
                  "ru": "Шип"
                }
              ]
            },
            {
              "code": "shape",
              "type": "radio",
              "visible_when": {
                "state": "curved"
              },
              "options": [
                {
                  "code": "c_shaped",
                  "uz": "C-симон",
                  "ru": "С-образно"
                },
                {
                  "code": "s_shaped",
                  "uz": "С-симон",
                  "ru": "S-образно"
                }
              ]
            },
            {
              "code": "side",
              "type": "side",
              "visible_when": {
                "state": "curved"
              }
            },
            {
              "code": "part",
              "type": "radio",
              "visible_when": {
                "state": "curved"
              },
              "options": [
                {
                  "code": "cartilage",
                  "uz": "Тоғай қисмида",
                  "ru": "В хрящевом отделе"
                },
                {
                  "code": "bone",
                  "uz": "Суяк қисмида",
                  "ru": "В костном отделе"
                }
              ]
            }
          ]
        }
      ]
    },
    {
      "code": "pharyngoscopy",
      "icon": "😮",
      "name": {
        "uz": "ФАРИНГОСКОПИЯ",
        "ru": "ФАРИНГОСКОПИЯ"
      },
      "sections": [
        {
          "code": "mouth_opening",
          "name": {
            "uz": "Оғиз очилиши",
            "ru": "Открывание рта"
          },
          "fields": [
            {
              "code": "state",
              "type": "radio",
              "options": [
                {
                  "code": "free",
                  "uz": "Еркин",
                  "ru": "Свободное",
                  "is_norm": true
                },
                {
                  "code": "trismus",
                  "uz": "Тризм",
                  "ru": "Тризм"
                },
                {
                  "code": "painful",
                  "uz": "Оғриқли",
                  "ru": "Болезненное"
                }
              ]
            }
          ]
        },
        {
          "code": "oral_mucosa",
          "name": {
            "uz": "Оғиз шиллиқ қавати",
            "ru": "Слизистая оболочка полости рта"
          },
          "fields": [
            {
              "code": "color",
              "type": "radio",
              "options": [
                {
                  "code": "pale_pink",
                  "uz": "Оқартирилган пушти",
                  "ru": "Бледно-розовая",
                  "is_norm": true
                },
                {
                  "code": "hyperemic",
                  "uz": "Гиперемияланган",
                  "ru": "Гиперемирована"
                }
              ]
            },
            {
              "code": "pathology",
              "type": "checkbox_multi",
              "options": [
                {
                  "code": "aphthae",
                  "uz": "Афталар",
                  "ru": "Афты"
                },
                {
                  "code": "ulcers",
                  "uz": "Яралар",
                  "ru": "Язвы"
                }
              ]
            },
            {
              "code": "location",
              "type": "checkbox_multi",
              "options": [
                {
                  "code": "tongue",
                  "uz": "Тил",
                  "ru": "Язык"
                },
                {
                  "code": "soft_palate",
                  "uz": "Юмшоқ танглай",
                  "ru": "Мягкое небо"
                },
                {
                  "code": "mouth_floor",
                  "uz": "Оғиз туби",
                  "ru": "Дно полости рта"
                }
              ]
            }
          ]
        },
        {
          "code": "tongue",
          "name": {
            "uz": "Тил",
            "ru": "Язык"
          },
          "fields": [
            {
              "code": "state",
              "type": "radio",
              "options": [
                {
                  "code": "clean",
                  "uz": "Тоза, нам",
                  "ru": "Чистый, влажный",
                  "is_norm": true
                },
                {
                  "code": "white_coat",
                  "uz": "Оқ караш билан қопланган",
                  "ru": "Обложен белым налетом"
                }
              ]
            },
            {
              "code": "pathology",
              "type": "checkbox_multi",
              "options": [
                {
                  "code": "aphtha",
                  "uz": "Афта",
                  "ru": "Афта"
                },
                {
                  "code": "ulcer",
                  "uz": "Яра",
                  "ru": "Язва"
                },
                {
                  "code": "infiltration",
                  "uz": "Инфилтратсия",
                  "ru": "Инфильтрация"
                }
              ]
            },
            {
              "code": "pain",
              "type": "radio",
              "options": [
                {
                  "code": "none",
                  "uz": "Оғриқ йўқ",
                  "ru": "Безболезненный",
                  "is_norm": true
                },
                {
                  "code": "present",
                  "uz": "Оғриқли",
                  "ru": "Болезненный"
                }
              ]
            },
            {
              "code": "side",
              "type": "side",
              "visible_when": {
                "pain": "present"
              }
            }
          ]
        },
        {
          "code": "teeth",
          "name": {
            "uz": "Тишлар",
            "ru": "Зубы"
          },
          "fields": [
            {
              "code": "state",
              "type": "radio",
              "options": [
                {
                  "code": "healthy",
                  "uz": "Соғлом",
                  "ru": "Здоровы",
                  "is_norm": true
                },
                {
                  "code": "sanitized",
                  "uz": "Санатсия қилинган",
                  "ru": "Санированы"
                },
                {
                  "code": "caries",
                  "uz": "Кариес",
                  "ru": "Кариес"
                }
              ]
            },
            {
              "code": "prostheses",
              "type": "checkbox",
              "label": {
                "uz": "Протезлар мавжуд",
                "ru": "Протезы имеются"
              }
            }
          ]
        },
        {
          "code": "palatine_arches",
          "name": {
            "uz": "Танглай ёйлари",
            "ru": "Небные дужки"
          },
          "fields": [
            {
              "code": "visibility",
              "type": "radio",
              "options": [
                {
                  "code": "well_visible",
                  "uz": "Яхши кўринади",
                  "ru": "Хорошо контурируются",
                  "is_norm": true
                },
                {
                  "code": "altered",
                  "uz": "Ўзгарган",
                  "ru": "Изменены"
                }
              ]
            },
            {
              "code": "pathology",
              "type": "checkbox_multi",
              "options": [
                {
                  "code": "edema",
                  "uz": "Шишган",
                  "ru": "Отечны"
                },
                {
                  "code": "hyperemic",
                  "uz": "Гиперемияланган",
                  "ru": "Гиперемированы"
                },
                {
                  "code": "infiltrated",
                  "uz": "Инфилтратсияланган",
                  "ru": "Инфильтрированы"
                },
                {
                  "code": "adherent",
                  "uz": "Бодомсимон без билан ёпишган",
                  "ru": "Спаяны с миндалиной"
                }
              ]
            },
            {
              "code": "features",
              "type": "checkbox_multi",
              "options": [
                {
                  "code": "cushion",
                  "uz": "Ёстиқсимон бўртиш",
                  "ru": "Подушкообразное выпячивание"
                },
                {
                  "code": "hiss_fold",
                  "uz": "Гисс бурмаси қалинлашган",
                  "ru": "Складка Гиса утолщена"
                }
              ]
            }
          ]
        },
        {
          "code": "palatine_tonsils",
          "name": {
            "uz": "Танглай бодомсимон безлари",
            "ru": "Небные миндалины"
          },
          "fields": [
            {
              "code": "state",
              "type": "radio",
              "options": [
                {
                  "code": "not_protruding",
                  "uz": "Танглай ёйидан чиқмайди",
                  "ru": "Не выступают из-за дужек",
                  "is_norm": true
                },
                {
                  "code": "hypertrophied",
                  "uz": "Гипертрофия",
                  "ru": "Гипертрофия"
                }
              ]
            },
            {
              "code": "hypertrophy_degree",
              "type": "degree",
              "visible_when": {
                "state": "hypertrophied"
              }
            },
            {
              "code": "surface",
              "type": "radio",
              "options": [
                {
                  "code": "smooth",
                  "uz": "Силлиқ",
                  "ru": "Гладкая",
                  "is_norm": true
                },
                {
                  "code": "bumpy",
                  "uz": "Ғадир-будир",
                  "ru": "Бугристая"
                }
              ]
            },
            {
              "code": "lacunae",
              "type": "radio",
              "options": [
                {
                  "code": "not_dilated",
                  "uz": "Лакуналар кенгаймаган",
                  "ru": "Лакуны не расширены",
                  "is_norm": true
                },
                {
                  "code": "dilated",
                  "uz": "Лакуналар кенгайган",
                  "ru": "Лакуны расширены"
                }
              ]
            },
            {
              "code": "lacunae_contents",
              "type": "checkbox_multi",
              "options": [
                {
                  "code": "none",
                  "uz": "Йўқ",
                  "ru": "Нет",
                  "is_norm": true
                },
                {
                  "code": "caseous_plugs",
                  "uz": "Казеоз тиқинлар",
                  "ru": "Казеозные пробки"
                },
                {
                  "code": "purulent_plugs",
                  "uz": "Йирингли тиқинлар",
                  "ru": "Гнойные пробки"
                },
                {
                  "code": "mucous_plugs",
                  "uz": "Шиллиқ тиқинлар",
                  "ru": "Слизистые пробки"
                },
                {
                  "code": "pus",
                  "uz": "Йиринг",
                  "ru": "Гной"
                },
                {
                  "code": "mucus",
                  "uz": "Шиллиқ",
                  "ru": "Слизь"
                }
              ]
            }
          ]
        },
        {
          "code": "posterior_pharynx",
          "name": {
            "uz": "Ҳалқум орқа девори",
            "ru": "Задняя стенка глотки"
          },
          "fields": [
            {
              "code": "state",
              "type": "radio",
              "options": [
                {
                  "code": "pink_smooth",
                  "uz": "Пушти, силлиқ",
                  "ru": "Розовая, гладкая",
                  "is_norm": true
                },
                {
                  "code": "altered",
                  "uz": "Ўзгарган",
                  "ru": "Изменена"
                }
              ]
            },
            {
              "code": "pathology",
              "type": "checkbox_multi",
              "options": [
                {
                  "code": "granules_hyper",
                  "uz": "Лимфоид гранулалар гипертрофияси",
                  "ru": "Гипертрофия лимфоидных гранул"
                },
                {
                  "code": "lateral_hyper",
                  "uz": "Ён валиклар гипертрофияси",
                  "ru": "Гипертрофия боковых валиков"
                },
                {
                  "code": "atrophy",
                  "uz": "Атрофия",
                  "ru": "Атрофия"
                }
              ]
            },
            {
              "code": "contents",
              "type": "checkbox_multi",
              "options": [
                {
                  "code": "pus",
                  "uz": "Йиринг",
                  "ru": "Гной"
                },
                {
                  "code": "crusts",
                  "uz": "Қобиқлар",
                  "ru": "Корки"
                },
                {
                  "code": "mucus",
                  "uz": "Шиллиқ",
                  "ru": "Слизь"
                },
                {
                  "code": "blood",
                  "uz": "Қон",
                  "ru": "Кровь"
                }
              ]
            }
          ]
        },
        {
          "code": "pharyngeal_reflex",
          "name": {
            "uz": "Ҳалқум рефлекси",
            "ru": "Глоточный рефлекс"
          },
          "fields": [
            {
              "code": "state",
              "type": "radio",
              "options": [
                {
                  "code": "preserved",
                  "uz": "Сақланган",
                  "ru": "Сохранен",
                  "is_norm": true
                },
                {
                  "code": "reduced",
                  "uz": "Пасайган",
                  "ru": "Снижен"
                },
                {
                  "code": "elevated",
                  "uz": "Юқори",
                  "ru": "Высокий"
                }
              ]
            }
          ]
        },
        {
          "code": "posterior_choanae",
          "name": {
            "uz": "Хоаналар (орқа риноскопия)",
            "ru": "Хоаны (задняя риноскопия)"
          },
          "fields": [
            {
              "code": "state",
              "type": "radio",
              "options": [
                {
                  "code": "free",
                  "uz": "Еркин",
                  "ru": "Свободны",
                  "is_norm": true
                },
                {
                  "code": "closed",
                  "uz": "Ёпилган",
                  "ru": "Закрыты"
                }
              ]
            },
            {
              "code": "cause",
              "type": "checkbox_multi",
              "visible_when": {
                "state": "closed"
              },
              "options": [
                {
                  "code": "turbinate_hyper_inf",
                  "uz": "Пастки чиғаноқлар гипертрофияси",
                  "ru": "Гипертрофия нижних раковин"
                },
                {
                  "code": "turbinate_hyper_mid",
                  "uz": "Ўрта чиғаноқлар гипертрофияси",
                  "ru": "Гипертрофия средних раковин"
                },
                {
                  "code": "polyp",
                  "uz": "Полип",
                  "ru": "Полип"
                },
                {
                  "code": "tumor",
                  "uz": "Ўсма",
                  "ru": "Новообразование"
                },
                {
                  "code": "adenoids",
                  "uz": "Аденоидлар",
                  "ru": "Аденоиды"
                }
              ]
            }
          ]
        },
        {
          "code": "posterior_vault",
          "name": {
            "uz": "Гумбаз",
            "ru": "Свод"
          },
          "fields": [
            {
              "code": "state",
              "type": "radio",
              "options": [
                {
                  "code": "free",
                  "uz": "Еркин",
                  "ru": "Свободен",
                  "is_norm": true
                },
                {
                  "code": "tumor",
                  "uz": "Ўсма",
                  "ru": "Новообразование"
                },
                {
                  "code": "adenoids",
                  "uz": "Аденоидлар",
                  "ru": "Аденоиды"
                }
              ]
            },
            {
              "code": "adenoid_degree",
              "type": "degree",
              "visible_when": {
                "state": "adenoids"
              }
            }
          ]
        },
        {
          "code": "auditory_tubes",
          "name": {
            "uz": "Ешитув найлари оғзи",
            "ru": "Устья слуховых труб"
          },
          "fields": [
            {
              "code": "state",
              "type": "radio",
              "options": [
                {
                  "code": "well_visible",
                  "uz": "Яхши кўринади, еркин",
                  "ru": "Хорошо контурируются, свободны",
                  "is_norm": true
                },
                {
                  "code": "narrowed",
                  "uz": "Торайган",
                  "ru": "Сужены"
                }
              ]
            },
            {
              "code": "contents",
              "type": "checkbox_multi",
              "options": [
                {
                  "code": "mucus",
                  "uz": "Шиллиқ",
                  "ru": "Слизь"
                },
                {
                  "code": "pus",
                  "uz": "Йиринг",
                  "ru": "Гной"
                }
              ]
            },
            {
              "code": "hypertrophy",
              "type": "checkbox",
              "label": {
                "uz": "Най валиклари ва бодомсимон безлар гипертрофияси",
                "ru": "Гипертрофия трубных валиков и миндалин"
              }
            }
          ]
        }
      ]
    },
    {
      "code": "otoscopy",
      "icon": "👂",
      "name": {
        "uz": "ОТОСКОПИЯ (AD/AS)",
        "ru": "ОТОСКОПИЯ (AD/AS)"
      },
      "per_ear": true,
      "ears": [
        {
          "code": "AD",
          "uz": "AD (ўнг)",
          "ru": "AD (правое)"
        },
        {
          "code": "AS",
          "uz": "AS (чап)",
          "ru": "AS (левое)"
        }
      ],
      "sections": [
        {
          "code": "auricle_canal",
          "name": {
            "uz": "Қулоқ супраси ва ташқи ешитув йўли",
            "ru": "Ушная раковина и наружный слуховой проход"
          },
          "fields": [
            {
              "code": "shape",
              "type": "radio",
              "options": [
                {
                  "code": "normal",
                  "uz": "Тўғри шаклда",
                  "ru": "Правильной формы",
                  "is_norm": true
                },
                {
                  "code": "altered",
                  "uz": "Ўзгарган",
                  "ru": "Изменена"
                }
              ]
            },
            {
              "code": "canal_width",
              "type": "radio",
              "options": [
                {
                  "code": "normal",
                  "uz": "Нормал",
                  "ru": "Нормальный",
                  "is_norm": true
                },
                {
                  "code": "wide",
                  "uz": "Кенг",
                  "ru": "Широкий"
                },
                {
                  "code": "narrow",
                  "uz": "Тор",
                  "ru": "Узкий"
                }
              ]
            },
            {
              "code": "pathology",
              "type": "checkbox_multi",
              "options": [
                {
                  "code": "exostosis",
                  "uz": "Екзостоз",
                  "ru": "Экзостоз"
                },
                {
                  "code": "pain",
                  "uz": "Оғриқли",
                  "ru": "Болезненный"
                },
                {
                  "code": "infiltration",
                  "uz": "Инфилтратсия",
                  "ru": "Инфильтрация"
                },
                {
                  "code": "hyperemia",
                  "uz": "Гиперемия",
                  "ru": "Гиперемия"
                }
              ]
            },
            {
              "code": "pain_part",
              "type": "radio",
              "visible_when": {
                "pathology": "pain"
              },
              "options": [
                {
                  "code": "bone",
                  "uz": "Суяк қисми",
                  "ru": "Костная часть"
                },
                {
                  "code": "cartilage",
                  "uz": "Тоғай қисми",
                  "ru": "Хрящевая часть"
                }
              ]
            },
            {
              "code": "contents",
              "type": "checkbox_multi",
              "options": [
                {
                  "code": "clean",
                  "uz": "Тоза",
                  "ru": "Свободный",
                  "is_norm": true
                },
                {
                  "code": "cerumen",
                  "uz": "Олтингугурт",
                  "ru": "Сера"
                },
                {
                  "code": "crusts",
                  "uz": "Қобиқлар",
                  "ru": "Корки"
                },
                {
                  "code": "plug",
                  "uz": "Тиқин",
                  "ru": "Пробка"
                },
                {
                  "code": "pus",
                  "uz": "Йиринг",
                  "ru": "Гной"
                },
                {
                  "code": "blood",
                  "uz": "Қон",
                  "ru": "Кровь"
                },
                {
                  "code": "films",
                  "uz": "Пардалар",
                  "ru": "Пленки"
                }
              ]
            }
          ]
        },
        {
          "code": "tympanic_membrane",
          "name": {
            "uz": "Барабан пардаси",
            "ru": "Барабанная перепонка"
          },
          "fields": [
            {
              "code": "color",
              "type": "radio",
              "options": [
                {
                  "code": "pearly_gray",
                  "uz": "Марваридсимон кулранг",
                  "ru": "Перламутрово-серая",
                  "is_norm": true
                },
                {
                  "code": "hyperemic",
                  "uz": "Гиперемияланган",
                  "ru": "Гиперемирована"
                }
              ]
            },
            {
              "code": "landmarks",
              "type": "radio",
              "options": [
                {
                  "code": "visible",
                  "uz": "Яхши кўринади",
                  "ru": "Выражены хорошо",
                  "is_norm": true
                },
                {
                  "code": "not_visible",
                  "uz": "Яхши кўринмайди",
                  "ru": "Не выражены"
                }
              ]
            },
            {
              "code": "perforation",
              "type": "radio",
              "options": [
                {
                  "code": "none",
                  "uz": "Йўқ",
                  "ru": "Нет",
                  "is_norm": true
                },
                {
                  "code": "marginal",
                  "uz": "Чекка",
                  "ru": "Краевая"
                },
                {
                  "code": "central",
                  "uz": "Марказий",
                  "ru": "Некраевая (центральная)"
                }
              ]
            },
            {
              "code": "pathology",
              "type": "checkbox_multi",
              "options": [
                {
                  "code": "pulsating",
                  "uz": "Пулсатсияловчи рефлекс",
                  "ru": "Пульсирующий рефлекс"
                },
                {
                  "code": "infiltration",
                  "uz": "Инфилтратсия",
                  "ru": "Инфильтрация"
                },
                {
                  "code": "retraction",
                  "uz": "Ретраксия",
                  "ru": "Втянутость"
                },
                {
                  "code": "scars",
                  "uz": "Чандиқлар",
                  "ru": "Рубцы"
                },
                {
                  "code": "calcinates",
                  "uz": "Калсинатлар",
                  "ru": "Кальцинаты"
                }
              ]
            }
          ]
        },
        {
          "code": "tympanic_cavity",
          "name": {
            "uz": "Барабан бўшлиғи",
            "ru": "Барабанная полость"
          },
          "visible_when_perforation": true,
          "fields": [
            {
              "code": "contents",
              "type": "checkbox_multi",
              "options": [
                {
                  "code": "pus",
                  "uz": "Йиринг",
                  "ru": "Гной"
                },
                {
                  "code": "granulations",
                  "uz": "Гранулятсиялар",
                  "ru": "Грануляции"
                },
                {
                  "code": "polyp",
                  "uz": "Полип",
                  "ru": "Полип"
                },
                {
                  "code": "cholesteatoma",
                  "uz": "Холестеатома массалари",
                  "ru": "Холестеатомные массы"
                },
                {
                  "code": "blood",
                  "uz": "Қон",
                  "ru": "Кровь"
                }
              ]
            }
          ]
        }
      ]
    },
    {
      "code": "laryngoscopy",
      "icon": "🗣",
      "name": {
        "uz": "ЛАРИНГОСКОПИЯ",
        "ru": "ЛАРИНГОСКОПИЯ"
      },
      "sections": [
        {
          "code": "lingual_tonsil",
          "name": {
            "uz": "Тил бодомсимон бези",
            "ru": "Язычная миндалина"
          },
          "fields": [
            {
              "code": "state",
              "type": "radio",
              "options": [
                {
                  "code": "not_enlarged",
                  "uz": "Катталашмаган",
                  "ru": "Не увеличена",
                  "is_norm": true
                },
                {
                  "code": "enlarged",
                  "uz": "Катталашган",
                  "ru": "Увеличена"
                }
              ]
            },
            {
              "code": "features",
              "type": "checkbox_multi",
              "options": [
                {
                  "code": "no_plaque",
                  "uz": "Караш йўқ",
                  "ru": "Налетов нет",
                  "is_norm": true
                },
                {
                  "code": "hyperemic",
                  "uz": "Гиперемияланган",
                  "ru": "Гиперемирована"
                }
              ]
            }
          ]
        },
        {
          "code": "valleculae",
          "name": {
            "uz": "Валлекулалар",
            "ru": "Валлекулы"
          },
          "fields": [
            {
              "code": "state",
              "type": "radio",
              "options": [
                {
                  "code": "free",
                  "uz": "Еркин",
                  "ru": "Свободны",
                  "is_norm": true
                },
                {
                  "code": "altered",
                  "uz": "Ўзгарган",
                  "ru": "Изменены"
                }
              ]
            },
            {
              "code": "color",
              "type": "radio",
              "options": [
                {
                  "code": "pale_pink",
                  "uz": "Оқартирилган пушти",
                  "ru": "Бледно-розовая",
                  "is_norm": true
                },
                {
                  "code": "hyperemic",
                  "uz": "Гиперемияланган",
                  "ru": "Гиперемирована"
                }
              ]
            }
          ]
        },
        {
          "code": "pharynx_walls",
          "name": {
            "uz": "Орқа ва ён деворлар",
            "ru": "Задняя и боковые стенки"
          },
          "fields": [
            {
              "code": "color",
              "type": "radio",
              "options": [
                {
                  "code": "pale_pink",
                  "uz": "Оқартирилган пушти",
                  "ru": "Бледно-розовая",
                  "is_norm": true
                },
                {
                  "code": "hyperemic",
                  "uz": "Гиперемияланган",
                  "ru": "Гиперемирована"
                }
              ]
            },
            {
              "code": "pathology",
              "type": "checkbox_multi",
              "options": [
                {
                  "code": "edema",
                  "uz": "Шишган",
                  "ru": "Отечна"
                },
                {
                  "code": "infiltrated",
                  "uz": "Инфилтратсияланган",
                  "ru": "Инфильтрирована"
                }
              ]
            }
          ]
        },
        {
          "code": "external_larynx",
          "name": {
            "uz": "Ҳиқилдоқ ташқи кўриги",
            "ru": "Гортань — наружный осмотр"
          },
          "fields": [
            {
              "code": "contour",
              "type": "radio",
              "options": [
                {
                  "code": "well",
                  "uz": "Яхши контурланади",
                  "ru": "Хорошо контурируется",
                  "is_norm": true
                },
                {
                  "code": "altered",
                  "uz": "Ўзгарган",
                  "ru": "Изменена"
                }
              ]
            },
            {
              "code": "mobility",
              "type": "radio",
              "options": [
                {
                  "code": "passive_mobile",
                  "uz": "Пассив ҳаракатчан",
                  "ru": "Пассивно подвижна",
                  "is_norm": true
                },
                {
                  "code": "immobile",
                  "uz": "Ҳаракатсиз",
                  "ru": "Неподвижна"
                }
              ]
            },
            {
              "code": "shape",
              "type": "radio",
              "options": [
                {
                  "code": "normal",
                  "uz": "Тўғри шаклда",
                  "ru": "Правильной формы",
                  "is_norm": true
                },
                {
                  "code": "deformed",
                  "uz": "Деформатсия",
                  "ru": "Деформирована"
                }
              ]
            },
            {
              "code": "crepitus",
              "type": "radio",
              "options": [
                {
                  "code": "negative",
                  "uz": "«Тоғай қирсиллаши» манфий",
                  "ru": "Симптом «хруста хрящей» отрицательный",
                  "is_norm": true
                },
                {
                  "code": "positive",
                  "uz": "«Тоғай қирсиллаши» мусбат",
                  "ru": "Симптом «хруста хрящей» положительный"
                }
              ]
            }
          ]
        },
        {
          "code": "vocal_folds",
          "name": {
            "uz": "Овоз бойламлари",
            "ru": "Голосовые складки"
          },
          "fields": [
            {
              "code": "color",
              "type": "radio",
              "options": [
                {
                  "code": "whitish",
                  "uz": "Оқартирилган",
                  "ru": "Белесоватые",
                  "is_norm": true
                },
                {
                  "code": "hyperemic",
                  "uz": "Гиперемияланган",
                  "ru": "Гиперемированы"
                }
              ]
            },
            {
              "code": "state",
              "type": "radio",
              "options": [
                {
                  "code": "clean",
                  "uz": "Тоза",
                  "ru": "Чистые",
                  "is_norm": true
                },
                {
                  "code": "plaques",
                  "uz": "Карашлар мавжуд",
                  "ru": "Налеты"
                },
                {
                  "code": "tumor",
                  "uz": "Ўсма",
                  "ru": "Новообразование"
                },
                {
                  "code": "hypertrophy",
                  "uz": "Гипертрофия",
                  "ru": "Гипертрофия"
                }
              ]
            },
            {
              "code": "closure",
              "type": "radio",
              "options": [
                {
                  "code": "full",
                  "uz": "Фонатсияда тўлиқ ёпилади",
                  "ru": "Полностью смыкаются",
                  "is_norm": true
                },
                {
                  "code": "not_full",
                  "uz": "Фонатсияда тўлиқ ёпилмайди",
                  "ru": "Полностью не смыкаются"
                }
              ]
            },
            {
              "code": "movement",
              "type": "radio",
              "options": [
                {
                  "code": "free",
                  "uz": "Еркин",
                  "ru": "Свободные",
                  "is_norm": true
                },
                {
                  "code": "limited",
                  "uz": "Ҳаракати чекланган",
                  "ru": "Ограничены в движении"
                },
                {
                  "code": "immobile",
                  "uz": "Ҳаракатсиз",
                  "ru": "Неподвижны"
                }
              ]
            },
            {
              "code": "side",
              "type": "side",
              "visible_when": {
                "state": [
                  "plaques",
                  "tumor",
                  "hypertrophy"
                ]
              }
            }
          ]
        },
        {
          "code": "voice",
          "name": {
            "uz": "Овоз",
            "ru": "Голос"
          },
          "fields": [
            {
              "code": "state",
              "type": "radio",
              "options": [
                {
                  "code": "sonorous",
                  "uz": "Жарангдор",
                  "ru": "Звучный",
                  "is_norm": true
                },
                {
                  "code": "hoarse",
                  "uz": "Хириллаган",
                  "ru": "Хриплый"
                },
                {
                  "code": "aphonia",
                  "uz": "Афония",
                  "ru": "Афония"
                }
              ]
            }
          ]
        },
        {
          "code": "dyspnea",
          "name": {
            "uz": "Ҳансираш",
            "ru": "Одышка"
          },
          "fields": [
            {
              "code": "state",
              "type": "radio",
              "options": [
                {
                  "code": "none",
                  "uz": "Йўқ",
                  "ru": "Нет",
                  "is_norm": true
                },
                {
                  "code": "present",
                  "uz": "Бор",
                  "ru": "Есть"
                }
              ]
            },
            {
              "code": "type",
              "type": "radio",
              "visible_when": {
                "state": "present"
              },
              "options": [
                {
                  "code": "inspiratory",
                  "uz": "Инспиратор",
                  "ru": "Инспираторная"
                },
                {
                  "code": "expiratory",
                  "uz": "Експиратор",
                  "ru": "Экспираторная"
                },
                {
                  "code": "mixed",
                  "uz": "Аралаш",
                  "ru": "Смешанная"
                }
              ]
            },
            {
              "code": "when",
              "type": "radio",
              "visible_when": {
                "state": "present"
              },
              "options": [
                {
                  "code": "rest",
                  "uz": "Тинч ҳолатда",
                  "ru": "В покое"
                },
                {
                  "code": "exertion",
                  "uz": "Юкламада",
                  "ru": "При нагрузке"
                }
              ]
            }
          ]
        },
        {
          "code": "stenosis",
          "name": {
            "uz": "Ҳиқилдоқ стенози",
            "ru": "Стеноз гортани"
          },
          "fields": [
            {
              "code": "degree",
              "type": "degree"
            }
          ]
        }
      ]
    }
  ]
}
